[
  {
    "@cnfhash": "cnf2$431c70c8c48d21204bd5ba0585ec7ac888fc6694",
    "@filename": "11-trivial.cnf",
    "@md5sum": "eb0c90948fc7997ee8ccd16592fab5d4",
    "@sha1sum": "6034a4e6d91c82ad80892ef566af209fd4b29149",
    "@timestamp": "2016-08-02T08:32:11.514003",
    "@version": "1.0.0",
    "featuring": {
      "clause_variables_sd_mean": 0.5,
      "clauses_count": 6,
      "clauses_length_largest": 2,
      "clauses_length_mean": 2,
      "clauses_length_median": 2.0,
      "clauses_length_sd": 0.0,
      "clauses_length_smallest": 2,
      "connected_literal_components_count": 2,
      "connected_variable_components_count": 1,
      "definite_clauses_count": 6,
      "existential_literals_count": 0,
      "existential_positive_literals_count": 0,
      "false_trivial": true,
      "goal_clauses_count": 0,
      "literals_count": 12,
      "literals_frequency_15_to_20": 4,
      "literals_frequency_30_to_35": 4,
      "literals_frequency_entropy": 3.836591668108979,
      "literals_frequency_largest": 0.3333333333333333,
      "literals_frequency_mean": 0.25,
      "literals_frequency_median": 0.25,
      "literals_frequency_sd": 0.08333333333333333,
      "literals_frequency_smallest": 0.16666666666666666,
      "literals_occurence_one_count": 4,
      "nbclauses": 6,
      "nbvars": 4,
      "negative_literals_in_clause_largest": 1,
      "negative_literals_in_clause_mean": 1,
      "negative_literals_in_clause_smallest": 1,
      "negative_unit_clause_count": 0,
      "positive_literals_count": 6,
      "positive_literals_in_clause_largest": 1,
      "positive_literals_in_clause_mean": 1,
      "positive_literals_in_clause_median": 1.0,
      "positive_literals_in_clause_sd": 0.0,
      "positive_literals_in_clause_smallest": 1,
      "positive_negative_literals_in_clause_ratio_entropy": 3.0,
      "positive_negative_literals_in_clause_ratio_mean": 0.5,
      "positive_unit_clause_count": 0,
      "tautological_literals_count": 0,
      "true_trivial": true,
      "two_literals_clause_count": 6,
      "variables_frequency_30_to_35": 2,
      "variables_frequency_65_to_70": 2,
      "variables_frequency_entropy": 1.8365916681089791,
      "variables_frequency_largest": 0.6666666666666666,
      "variables_frequency_mean": 0.5,
      "variables_frequency_median": 0.5,
      "variables_frequency_sd": 0.16666666666666666,
      "variables_frequency_smallest": 0.3333333333333333,
      "variables_largest": 4,
      "variables_smallest": 1,
      "variables_used_count": 4
    }
  }
]
